dataframe_show_reader/__init__.py
dataframe_show_reader/assert_equal_dataframe.py
dataframe_show_reader/dataframe_show_reader.py
py_dataframe_show_reader-1.0.0.dist-info/LICENSE
py_dataframe_show_reader-1.0.0.dist-info/METADATA
py_dataframe_show_reader-1.0.0.dist-info/WHEEL
py_dataframe_show_reader-1.0.0.dist-info/top_level.txt
py_dataframe_show_reader-1.0.0.dist-info/RECORD
