Metadata-Version: 2.1
Name: py-dataframe-show-reader
Version: 1.0.0
Summary: Reads the output of a DataFrame.show() statement into a DataFrame
Home-page: https://github.com/internetsystemsgroup/py-dataframe-show-reader
Author: Steve Whalen
Author-email: sjwhalen@yahoo.com
License: UNKNOWN
Platform: UNKNOWN
Classifier: License :: OSI Approved :: Apache Software License
Classifier: Programming Language :: Python :: 3.6
Classifier: Programming Language :: Python :: 3.7
Requires-Dist: pyspark (>=2)
